{"osStr":"macOS","version":"13.7.5 RC 3","build":"22H520","restoreVersion":"22.8.520.0.0,0","buildId":"9FB805EA-FB34-11EF-8192-07558361D399","embeddedOSBuild":"14Y910","bridgeOSBuild":"22P54236d","buildTrain":"RomeSecurityGlowE","released":"2025-03-10","rc":true,"appledbWebImage":{"id":"Ventura","align":"left"},"deviceMap":["iMac18,1","iMac18,2","iMac18,3","iMac19,1","iMac19,2","iMac20,1","iMac20,2","iMac21,1","iMac21,2","iMacPro1,1","Mac13,1","Mac13,2","Mac14,2","Mac14,3","Mac14,5","Mac14,6","Mac14,7","Mac14,8","Mac14,8-Rack","Mac14,9","Mac14,10","Mac14,12","Mac14,13","Mac14,14","Mac14,15","Mac15,3","Mac15,4","Mac15,5","MacBook10,1","MacBookAir8,1","MacBookAir8,2","MacBookAir9,1","MacBookAir10,1","MacBookPro14,1","MacBookPro14,2","MacBookPro14,3","MacBookPro15,1-2018","MacBookPro15,1-2019","MacBookPro15,2-2018","MacBookPro15,2-2019","MacBookPro15,3-2018","MacBookPro15,3-2019","MacBookPro15,4","MacBookPro16,1","MacBookPro16,2","MacBookPro16,3","MacBookPro16,4","MacBookPro17,1","MacBookPro18,1","MacBookPro18,2","MacBookPro18,3","MacBookPro18,4","Macmini8,1","Macmini9,1","MacPro7,1","MacPro7,1-Rack","VirtualMac2,1"],"sources":[{"type":"installassistant","deviceMap":["iMac18,1","iMac18,2","iMac18,3","iMac19,1","iMac19,2","iMac20,1","iMac20,2","iMac21,1","iMac21,2","iMacPro1,1","Mac13,1","Mac13,2","Mac14,2","Mac14,3","Mac14,5","Mac14,6","Mac14,7","Mac14,8","Mac14,8-Rack","Mac14,9","Mac14,10","Mac14,12","Mac14,13","Mac14,14","Mac14,15","Mac15,3","Mac15,4","Mac15,5","MacBook10,1","MacBookAir8,1","MacBookAir8,2","MacBookAir9,1","MacBookAir10,1","MacBookPro14,1","MacBookPro14,2","MacBookPro14,3","MacBookPro15,1-2018","MacBookPro15,1-2019","MacBookPro15,2-2018","MacBookPro15,2-2019","MacBookPro15,3-2018","MacBookPro15,3-2019","MacBookPro15,4","MacBookPro16,1","MacBookPro16,2","MacBookPro16,3","MacBookPro16,4","MacBookPro17,1","MacBookPro18,1","MacBookPro18,2","MacBookPro18,3","MacBookPro18,4","Macmini8,1","Macmini9,1","MacPro7,1","MacPro7,1-Rack","VirtualMac2,1"],"links":[{"url":"https://swcdn.apple.com/content/downloads/45/09/072-97952-A_D4XP9YQOR4/ufl1lu1nuveftnddbv7uvfk6isqbgs18nd/InstallAssistant.pkg","catalog":"dev-beta","preferred":true,"active":false},{"url":"http://swcdn.apple.com/content/downloads/45/09/072-97952-A_D4XP9YQOR4/ufl1lu1nuveftnddbv7uvfk6isqbgs18nd/InstallAssistant.pkg","catalog":"dev-beta","preferred":false,"active":false},{"url":"https://swcdn.apple.com/content/downloads/01/58/072-97952-A_TLAAIYE2NA/12lyo6cavbamxezvrltmdclfc0id9gh7j2/InstallAssistant.pkg","catalog":"public-beta","preferred":false,"active":false},{"url":"http://swcdn.apple.com/content/downloads/01/58/072-97952-A_TLAAIYE2NA/12lyo6cavbamxezvrltmdclfc0id9gh7j2/InstallAssistant.pkg","catalog":"public-beta","preferred":false,"active":false}],"hashes":{"sha1":"8193dfe229c02099e21a92f4f840a8696fe3f351"},"size":12202314647},{"type":"ota","deviceMap":["iMac18,1","iMac18,2","iMac18,3","iMac19,1","iMac19,2","iMac20,1","iMac20,2","iMac21,1","iMac21,2","iMacPro1,1","Mac13,1","Mac13,2","Mac14,2","Mac14,3","Mac14,5","Mac14,6","Mac14,7","Mac14,8","Mac14,8-Rack","Mac14,9","Mac14,10","Mac14,12","Mac14,13","Mac14,14","Mac14,15","Mac15,3","Mac15,4","Mac15,5","MacBook10,1","MacBookAir8,1","MacBookAir8,2","MacBookAir9,1","MacBookAir10,1","MacBookPro14,1","MacBookPro14,2","MacBookPro14,3","MacBookPro15,1-2018","MacBookPro15,1-2019","MacBookPro15,2-2018","MacBookPro15,2-2019","MacBookPro15,3-2018","MacBookPro15,3-2019","MacBookPro15,4","MacBookPro16,1","MacBookPro16,2","MacBookPro16,3","MacBookPro16,4","MacBookPro17,1","MacBookPro18,1","MacBookPro18,2","MacBookPro18,3","MacBookPro18,4","Macmini8,1","Macmini9,1","MacPro7,1","MacPro7,1-Rack","VirtualMac2,1"],"links":[{"url":"https://updates.cdn-apple.com/2025WinterSeed/patches/072-97962/F96FD6A9-691F-4C50-8ED5-74E71B6AD97F/com_apple_MobileAsset_MacSoftwareUpdate/33cea4e304bdb33cce788b642a5ef21f2ca2518e.zip","preferred":true,"active":true},{"url":"http://updates-http.cdn-apple.com/2025WinterSeed/patches/072-97962/F96FD6A9-691F-4C50-8ED5-74E71B6AD97F/com_apple_MobileAsset_MacSoftwareUpdate/33cea4e304bdb33cce788b642a5ef21f2ca2518e.zip","preferred":false,"active":true}],"hashes":{"sha1":"5822fd11d3c2f5532ff39a32746d3576b0f7f0c2","sha2-256":"636144ab44491afdf86269934d3dbc111ec493959298d84489b948d79acbc374"},"size":12182406913},{"type":"ota","prerequisiteBuild":"22H417","deviceMap":["iMac18,1","iMac18,2","iMac18,3","iMac19,1","iMac19,2","iMac20,1","iMac20,2","iMacPro1,1","MacBook10,1","MacBookAir8,1","MacBookAir8,2","MacBookAir9,1","MacBookPro14,1","MacBookPro14,2","MacBookPro14,3","MacBookPro15,1-2018","MacBookPro15,1-2019","MacBookPro15,2-2018","MacBookPro15,2-2019","MacBookPro15,3-2018","MacBookPro15,3-2019","MacBookPro15,4","MacBookPro16,1","MacBookPro16,2","MacBookPro16,3","MacBookPro16,4","Macmini8,1","MacPro7,1","MacPro7,1-Rack"],"links":[{"url":"https://updates.cdn-apple.com/2025WinterSeed/patches/072-97954/6AA70880-D9FC-41EE-A41C-C100200103F3/com_apple_MobileAsset_MacSoftwareUpdate/1bca83b4ebf1c4b57c9c2eea8c93afe2c3b2a4ca.zip","preferred":true,"active":true},{"url":"http://updates-http.cdn-apple.com/2025WinterSeed/patches/072-97954/6AA70880-D9FC-41EE-A41C-C100200103F3/com_apple_MobileAsset_MacSoftwareUpdate/1bca83b4ebf1c4b57c9c2eea8c93afe2c3b2a4ca.zip","preferred":false,"active":true}],"hashes":{"sha1":"6bce90a2fb742bba2f2b76af72cad86ab59bb03d","sha2-256":"f78885d81ce9f5a4ebba325afec4129fac04b3df93fd80f30a33a874ba2c4377"},"size":663950226},{"type":"ota","prerequisiteBuild":"22H417","deviceMap":["iMac21,1","iMac21,2","Mac13,1","Mac13,2","Mac14,2","Mac14,3","Mac14,5","Mac14,6","Mac14,7","Mac14,8","Mac14,8-Rack","Mac14,9","Mac14,10","Mac14,12","Mac14,13","Mac14,14","Mac14,15","Mac15,3","Mac15,4","Mac15,5","MacBookAir10,1","MacBookPro17,1","MacBookPro18,1","MacBookPro18,2","MacBookPro18,3","MacBookPro18,4","Macmini9,1","VirtualMac2,1"],"links":[{"url":"https://updates.cdn-apple.com/2025WinterSeed/patches/072-97960/78FF98B1-A284-47C9-8C23-180D7301608F/com_apple_MobileAsset_MacSoftwareUpdate/ea66b2014a8bd0bcb4aa857723b5b9e69e727cab.zip","preferred":true,"active":true},{"url":"http://updates-http.cdn-apple.com/2025WinterSeed/patches/072-97960/78FF98B1-A284-47C9-8C23-180D7301608F/com_apple_MobileAsset_MacSoftwareUpdate/ea66b2014a8bd0bcb4aa857723b5b9e69e727cab.zip","preferred":false,"active":true}],"hashes":{"sha1":"98ac297cb118e26272727794ffe694fffef6457d","sha2-256":"699e6a633e600572ff5e53b068d368cbab5ccc6b1fd3966b26d470fcf3cdad4e"},"size":1156626030},{"type":"ota","prerequisiteBuild":"22H420","deviceMap":["iMac18,1","iMac18,2","iMac18,3","iMac19,1","iMac19,2","iMac20,1","iMac20,2","iMacPro1,1","MacBook10,1","MacBookAir8,1","MacBookAir8,2","MacBookAir9,1","MacBookPro14,1","MacBookPro14,2","MacBookPro14,3","MacBookPro15,1-2018","MacBookPro15,1-2019","MacBookPro15,2-2018","MacBookPro15,2-2019","MacBookPro15,3-2018","MacBookPro15,3-2019","MacBookPro15,4","MacBookPro16,1","MacBookPro16,2","MacBookPro16,3","MacBookPro16,4","Macmini8,1","MacPro7,1","MacPro7,1-Rack"],"links":[{"url":"https://updates.cdn-apple.com/2025WinterSeed/patches/072-97953/13B96EC6-D091-456E-8C4C-452205AA267C/com_apple_MobileAsset_MacSoftwareUpdate/3ba5f5575b2ebf0a7e92735685e8706d9b922fea.zip","preferred":true,"active":true},{"url":"http://updates-http.cdn-apple.com/2025WinterSeed/patches/072-97953/13B96EC6-D091-456E-8C4C-452205AA267C/com_apple_MobileAsset_MacSoftwareUpdate/3ba5f5575b2ebf0a7e92735685e8706d9b922fea.zip","preferred":false,"active":true}],"hashes":{"sha1":"4dded9789a2df8adcddba33a1249b1f1e0e45922","sha2-256":"49352c7d9e8a5f3fbdd41540eef10d395f3c704476687fc85bf48cdf55a59f81"},"size":664213025},{"type":"ota","prerequisiteBuild":"22H420","deviceMap":["iMac21,1","iMac21,2","Mac13,1","Mac13,2","Mac14,2","Mac14,3","Mac14,5","Mac14,6","Mac14,7","Mac14,8","Mac14,8-Rack","Mac14,9","Mac14,10","Mac14,12","Mac14,13","Mac14,14","Mac14,15","Mac15,3","Mac15,4","Mac15,5","MacBookAir10,1","MacBookPro17,1","MacBookPro18,1","MacBookPro18,2","MacBookPro18,3","MacBookPro18,4","Macmini9,1","VirtualMac2,1"],"links":[{"url":"https://updates.cdn-apple.com/2025WinterSeed/patches/072-97956/3E1E7E08-A00E-4C2B-9204-62B534F78271/com_apple_MobileAsset_MacSoftwareUpdate/ca09c4e2fa54ab03b6a4d8cb2ace6669c652f78b.zip","preferred":true,"active":true},{"url":"http://updates-http.cdn-apple.com/2025WinterSeed/patches/072-97956/3E1E7E08-A00E-4C2B-9204-62B534F78271/com_apple_MobileAsset_MacSoftwareUpdate/ca09c4e2fa54ab03b6a4d8cb2ace6669c652f78b.zip","preferred":false,"active":true}],"hashes":{"sha1":"996978749c4e790647cc1d8c9a5d081ae43dee40","sha2-256":"febfe4db7f05ceac0eeff86846cba8f2603124c4a47bbe395e030e21b04d71d9"},"size":1158043475},{"type":"ota","prerequisiteBuild":"22H510","deviceMap":["iMac18,1","iMac18,2","iMac18,3","iMac19,1","iMac19,2","iMac20,1","iMac20,2","iMacPro1,1","MacBook10,1","MacBookAir8,1","MacBookAir8,2","MacBookAir9,1","MacBookPro14,1","MacBookPro14,2","MacBookPro14,3","MacBookPro15,1-2018","MacBookPro15,1-2019","MacBookPro15,2-2018","MacBookPro15,2-2019","MacBookPro15,3-2018","MacBookPro15,3-2019","MacBookPro15,4","MacBookPro16,1","MacBookPro16,2","MacBookPro16,3","MacBookPro16,4","Macmini8,1","MacPro7,1","MacPro7,1-Rack"],"links":[{"url":"https://updates.cdn-apple.com/2025WinterSeed/patches/072-97959/60D1C64E-B3BB-4EB3-A9BE-8E2D0A02507B/com_apple_MobileAsset_MacSoftwareUpdate/19f31f09637517baf3ab4830731065f77a61e5c4.zip","preferred":true,"active":true},{"url":"http://updates-http.cdn-apple.com/2025WinterSeed/patches/072-97959/60D1C64E-B3BB-4EB3-A9BE-8E2D0A02507B/com_apple_MobileAsset_MacSoftwareUpdate/19f31f09637517baf3ab4830731065f77a61e5c4.zip","preferred":false,"active":true}],"hashes":{"sha1":"08582ff99a038fdd4ca87f2479e7479f9a7467fe","sha2-256":"109d58f49774006322fa36db96482db341651c152414b15903d9bc26aa62e6d5"},"size":631025739},{"type":"ota","prerequisiteBuild":"22H510","deviceMap":["iMac21,1","iMac21,2","Mac13,1","Mac13,2","Mac14,2","Mac14,3","Mac14,5","Mac14,6","Mac14,7","Mac14,8","Mac14,8-Rack","Mac14,9","Mac14,10","Mac14,12","Mac14,13","Mac14,14","Mac14,15","Mac15,3","Mac15,4","Mac15,5","MacBookAir10,1","MacBookPro17,1","MacBookPro18,1","MacBookPro18,2","MacBookPro18,3","MacBookPro18,4","Macmini9,1","VirtualMac2,1"],"links":[{"url":"https://updates.cdn-apple.com/2025WinterSeed/patches/072-97964/90C2B3C2-D980-44C4-9004-B09FC3066678/com_apple_MobileAsset_MacSoftwareUpdate/e85f2ebcc20f03b33b9de3addc3673f327a13da5.zip","preferred":true,"active":true},{"url":"http://updates-http.cdn-apple.com/2025WinterSeed/patches/072-97964/90C2B3C2-D980-44C4-9004-B09FC3066678/com_apple_MobileAsset_MacSoftwareUpdate/e85f2ebcc20f03b33b9de3addc3673f327a13da5.zip","preferred":false,"active":true}],"hashes":{"sha1":"de48dc81ef21001a05f693d4dfd53921f255b0ea","sha2-256":"d181b314ad8c626a8e18b4840eef3eb505fc307544f678223617998dc23c5475"},"size":1089874209},{"type":"ota","prerequisiteBuild":"22H515","deviceMap":["iMac18,1","iMac18,2","iMac18,3","iMac19,1","iMac19,2","iMac20,1","iMac20,2","iMacPro1,1","MacBook10,1","MacBookAir8,1","MacBookAir8,2","MacBookAir9,1","MacBookPro14,1","MacBookPro14,2","MacBookPro14,3","MacBookPro15,1-2018","MacBookPro15,1-2019","MacBookPro15,2-2018","MacBookPro15,2-2019","MacBookPro15,3-2018","MacBookPro15,3-2019","MacBookPro15,4","MacBookPro16,1","MacBookPro16,2","MacBookPro16,3","MacBookPro16,4","Macmini8,1","MacPro7,1","MacPro7,1-Rack"],"links":[{"url":"https://updates.cdn-apple.com/2025WinterSeed/patches/072-98588/ACF393E4-D430-4B3D-861A-E398659B8936/com_apple_MobileAsset_MacSoftwareUpdate/db6031c6ba03f10f5b42d74921574cb0a45aec94.zip","preferred":true,"active":true},{"url":"http://updates-http.cdn-apple.com/2025WinterSeed/patches/072-98588/ACF393E4-D430-4B3D-861A-E398659B8936/com_apple_MobileAsset_MacSoftwareUpdate/db6031c6ba03f10f5b42d74921574cb0a45aec94.zip","preferred":false,"active":true}],"hashes":{"sha1":"602bb3e93ea334cadce27a2cb6d4924b2f96a8ce","sha2-256":"870c1ecbf50e0e957a61bec58833a75d78b816d9d6a70dbf13fdf26c93cd65d3"},"size":534901441},{"type":"ota","prerequisiteBuild":"22H515","deviceMap":["iMac21,1","iMac21,2","Mac13,1","Mac13,2","Mac14,2","Mac14,3","Mac14,5","Mac14,6","Mac14,7","Mac14,8","Mac14,8-Rack","Mac14,9","Mac14,10","Mac14,12","Mac14,13","Mac14,14","Mac14,15","Mac15,3","Mac15,4","Mac15,5","MacBookAir10,1","MacBookPro17,1","MacBookPro18,1","MacBookPro18,2","MacBookPro18,3","MacBookPro18,4","Macmini9,1","VirtualMac2,1"],"links":[{"url":"https://updates.cdn-apple.com/2025WinterSeed/patches/072-98589/05809F7A-79E7-46D9-9DF0-5FDB2AF2A47C/com_apple_MobileAsset_MacSoftwareUpdate/2acc00731b79e50693747cd48e715ab4f99a34f5.zip","preferred":true,"active":true},{"url":"http://updates-http.cdn-apple.com/2025WinterSeed/patches/072-98589/05809F7A-79E7-46D9-9DF0-5FDB2AF2A47C/com_apple_MobileAsset_MacSoftwareUpdate/2acc00731b79e50693747cd48e715ab4f99a34f5.zip","preferred":false,"active":true}],"hashes":{"sha1":"721f971dcfff9b27aa50685722508ad4261ac2e3","sha2-256":"1418c39d747282a00091dbb2a5bd83218cd49fbf813638949602f93843ab4d6d"},"size":943989893}],"uniqueBuild":"22H520","key":"macOS;22H520","beta":false,"preinstalled":[],"preinstalledOS":[],"signed":[],"osType":"macOS","devices":{"iMac18,1":{"installassistant":"https://swcdn.apple.com/content/downloads/45/09/072-97952-A_D4XP9YQOR4/ufl1lu1nuveftnddbv7uvfk6isqbgs18nd/InstallAssistant.pkg"},"iMac18,2":{"installassistant":"https://swcdn.apple.com/content/downloads/45/09/072-97952-A_D4XP9YQOR4/ufl1lu1nuveftnddbv7uvfk6isqbgs18nd/InstallAssistant.pkg"},"iMac18,3":{"installassistant":"https://swcdn.apple.com/content/downloads/45/09/072-97952-A_D4XP9YQOR4/ufl1lu1nuveftnddbv7uvfk6isqbgs18nd/InstallAssistant.pkg"},"iMac19,1":{"installassistant":"https://swcdn.apple.com/content/downloads/45/09/072-97952-A_D4XP9YQOR4/ufl1lu1nuveftnddbv7uvfk6isqbgs18nd/InstallAssistant.pkg"},"iMac19,2":{"installassistant":"https://swcdn.apple.com/content/downloads/45/09/072-97952-A_D4XP9YQOR4/ufl1lu1nuveftnddbv7uvfk6isqbgs18nd/InstallAssistant.pkg"},"iMac20,1":{"installassistant":"https://swcdn.apple.com/content/downloads/45/09/072-97952-A_D4XP9YQOR4/ufl1lu1nuveftnddbv7uvfk6isqbgs18nd/InstallAssistant.pkg"},"iMac20,2":{"installassistant":"https://swcdn.apple.com/content/downloads/45/09/072-97952-A_D4XP9YQOR4/ufl1lu1nuveftnddbv7uvfk6isqbgs18nd/InstallAssistant.pkg"},"iMac21,1":{"installassistant":"https://swcdn.apple.com/content/downloads/45/09/072-97952-A_D4XP9YQOR4/ufl1lu1nuveftnddbv7uvfk6isqbgs18nd/InstallAssistant.pkg"},"iMac21,2":{"installassistant":"https://swcdn.apple.com/content/downloads/45/09/072-97952-A_D4XP9YQOR4/ufl1lu1nuveftnddbv7uvfk6isqbgs18nd/InstallAssistant.pkg"},"iMacPro1,1":{"installassistant":"https://swcdn.apple.com/content/downloads/45/09/072-97952-A_D4XP9YQOR4/ufl1lu1nuveftnddbv7uvfk6isqbgs18nd/InstallAssistant.pkg"},"Mac13,1":{"installassistant":"https://swcdn.apple.com/content/downloads/45/09/072-97952-A_D4XP9YQOR4/ufl1lu1nuveftnddbv7uvfk6isqbgs18nd/InstallAssistant.pkg"},"Mac13,2":{"installassistant":"https://swcdn.apple.com/content/downloads/45/09/072-97952-A_D4XP9YQOR4/ufl1lu1nuveftnddbv7uvfk6isqbgs18nd/InstallAssistant.pkg"},"Mac14,2":{"installassistant":"https://swcdn.apple.com/content/downloads/45/09/072-97952-A_D4XP9YQOR4/ufl1lu1nuveftnddbv7uvfk6isqbgs18nd/InstallAssistant.pkg"},"Mac14,3":{"installassistant":"https://swcdn.apple.com/content/downloads/45/09/072-97952-A_D4XP9YQOR4/ufl1lu1nuveftnddbv7uvfk6isqbgs18nd/InstallAssistant.pkg"},"Mac14,5":{"installassistant":"https://swcdn.apple.com/content/downloads/45/09/072-97952-A_D4XP9YQOR4/ufl1lu1nuveftnddbv7uvfk6isqbgs18nd/InstallAssistant.pkg"},"Mac14,6":{"installassistant":"https://swcdn.apple.com/content/downloads/45/09/072-97952-A_D4XP9YQOR4/ufl1lu1nuveftnddbv7uvfk6isqbgs18nd/InstallAssistant.pkg"},"Mac14,7":{"installassistant":"https://swcdn.apple.com/content/downloads/45/09/072-97952-A_D4XP9YQOR4/ufl1lu1nuveftnddbv7uvfk6isqbgs18nd/InstallAssistant.pkg"},"Mac14,8":{"installassistant":"https://swcdn.apple.com/content/downloads/45/09/072-97952-A_D4XP9YQOR4/ufl1lu1nuveftnddbv7uvfk6isqbgs18nd/InstallAssistant.pkg"},"Mac14,8-Rack":{"installassistant":"https://swcdn.apple.com/content/downloads/45/09/072-97952-A_D4XP9YQOR4/ufl1lu1nuveftnddbv7uvfk6isqbgs18nd/InstallAssistant.pkg"},"Mac14,9":{"installassistant":"https://swcdn.apple.com/content/downloads/45/09/072-97952-A_D4XP9YQOR4/ufl1lu1nuveftnddbv7uvfk6isqbgs18nd/InstallAssistant.pkg"},"Mac14,10":{"installassistant":"https://swcdn.apple.com/content/downloads/45/09/072-97952-A_D4XP9YQOR4/ufl1lu1nuveftnddbv7uvfk6isqbgs18nd/InstallAssistant.pkg"},"Mac14,12":{"installassistant":"https://swcdn.apple.com/content/downloads/45/09/072-97952-A_D4XP9YQOR4/ufl1lu1nuveftnddbv7uvfk6isqbgs18nd/InstallAssistant.pkg"},"Mac14,13":{"installassistant":"https://swcdn.apple.com/content/downloads/45/09/072-97952-A_D4XP9YQOR4/ufl1lu1nuveftnddbv7uvfk6isqbgs18nd/InstallAssistant.pkg"},"Mac14,14":{"installassistant":"https://swcdn.apple.com/content/downloads/45/09/072-97952-A_D4XP9YQOR4/ufl1lu1nuveftnddbv7uvfk6isqbgs18nd/InstallAssistant.pkg"},"Mac14,15":{"installassistant":"https://swcdn.apple.com/content/downloads/45/09/072-97952-A_D4XP9YQOR4/ufl1lu1nuveftnddbv7uvfk6isqbgs18nd/InstallAssistant.pkg"},"Mac15,3":{"installassistant":"https://swcdn.apple.com/content/downloads/45/09/072-97952-A_D4XP9YQOR4/ufl1lu1nuveftnddbv7uvfk6isqbgs18nd/InstallAssistant.pkg"},"Mac15,4":{"installassistant":"https://swcdn.apple.com/content/downloads/45/09/072-97952-A_D4XP9YQOR4/ufl1lu1nuveftnddbv7uvfk6isqbgs18nd/InstallAssistant.pkg"},"Mac15,5":{"installassistant":"https://swcdn.apple.com/content/downloads/45/09/072-97952-A_D4XP9YQOR4/ufl1lu1nuveftnddbv7uvfk6isqbgs18nd/InstallAssistant.pkg"},"MacBook10,1":{"installassistant":"https://swcdn.apple.com/content/downloads/45/09/072-97952-A_D4XP9YQOR4/ufl1lu1nuveftnddbv7uvfk6isqbgs18nd/InstallAssistant.pkg"},"MacBookAir8,1":{"installassistant":"https://swcdn.apple.com/content/downloads/45/09/072-97952-A_D4XP9YQOR4/ufl1lu1nuveftnddbv7uvfk6isqbgs18nd/InstallAssistant.pkg"},"MacBookAir8,2":{"installassistant":"https://swcdn.apple.com/content/downloads/45/09/072-97952-A_D4XP9YQOR4/ufl1lu1nuveftnddbv7uvfk6isqbgs18nd/InstallAssistant.pkg"},"MacBookAir9,1":{"installassistant":"https://swcdn.apple.com/content/downloads/45/09/072-97952-A_D4XP9YQOR4/ufl1lu1nuveftnddbv7uvfk6isqbgs18nd/InstallAssistant.pkg"},"MacBookAir10,1":{"installassistant":"https://swcdn.apple.com/content/downloads/45/09/072-97952-A_D4XP9YQOR4/ufl1lu1nuveftnddbv7uvfk6isqbgs18nd/InstallAssistant.pkg"},"MacBookPro14,1":{"installassistant":"https://swcdn.apple.com/content/downloads/45/09/072-97952-A_D4XP9YQOR4/ufl1lu1nuveftnddbv7uvfk6isqbgs18nd/InstallAssistant.pkg"},"MacBookPro14,2":{"installassistant":"https://swcdn.apple.com/content/downloads/45/09/072-97952-A_D4XP9YQOR4/ufl1lu1nuveftnddbv7uvfk6isqbgs18nd/InstallAssistant.pkg"},"MacBookPro14,3":{"installassistant":"https://swcdn.apple.com/content/downloads/45/09/072-97952-A_D4XP9YQOR4/ufl1lu1nuveftnddbv7uvfk6isqbgs18nd/InstallAssistant.pkg"},"MacBookPro15,1-2018":{"installassistant":"https://swcdn.apple.com/content/downloads/45/09/072-97952-A_D4XP9YQOR4/ufl1lu1nuveftnddbv7uvfk6isqbgs18nd/InstallAssistant.pkg"},"MacBookPro15,1-2019":{"installassistant":"https://swcdn.apple.com/content/downloads/45/09/072-97952-A_D4XP9YQOR4/ufl1lu1nuveftnddbv7uvfk6isqbgs18nd/InstallAssistant.pkg"},"MacBookPro15,2-2018":{"installassistant":"https://swcdn.apple.com/content/downloads/45/09/072-97952-A_D4XP9YQOR4/ufl1lu1nuveftnddbv7uvfk6isqbgs18nd/InstallAssistant.pkg"},"MacBookPro15,2-2019":{"installassistant":"https://swcdn.apple.com/content/downloads/45/09/072-97952-A_D4XP9YQOR4/ufl1lu1nuveftnddbv7uvfk6isqbgs18nd/InstallAssistant.pkg"},"MacBookPro15,3-2018":{"installassistant":"https://swcdn.apple.com/content/downloads/45/09/072-97952-A_D4XP9YQOR4/ufl1lu1nuveftnddbv7uvfk6isqbgs18nd/InstallAssistant.pkg"},"MacBookPro15,3-2019":{"installassistant":"https://swcdn.apple.com/content/downloads/45/09/072-97952-A_D4XP9YQOR4/ufl1lu1nuveftnddbv7uvfk6isqbgs18nd/InstallAssistant.pkg"},"MacBookPro15,4":{"installassistant":"https://swcdn.apple.com/content/downloads/45/09/072-97952-A_D4XP9YQOR4/ufl1lu1nuveftnddbv7uvfk6isqbgs18nd/InstallAssistant.pkg"},"MacBookPro16,1":{"installassistant":"https://swcdn.apple.com/content/downloads/45/09/072-97952-A_D4XP9YQOR4/ufl1lu1nuveftnddbv7uvfk6isqbgs18nd/InstallAssistant.pkg"},"MacBookPro16,2":{"installassistant":"https://swcdn.apple.com/content/downloads/45/09/072-97952-A_D4XP9YQOR4/ufl1lu1nuveftnddbv7uvfk6isqbgs18nd/InstallAssistant.pkg"},"MacBookPro16,3":{"installassistant":"https://swcdn.apple.com/content/downloads/45/09/072-97952-A_D4XP9YQOR4/ufl1lu1nuveftnddbv7uvfk6isqbgs18nd/InstallAssistant.pkg"},"MacBookPro16,4":{"installassistant":"https://swcdn.apple.com/content/downloads/45/09/072-97952-A_D4XP9YQOR4/ufl1lu1nuveftnddbv7uvfk6isqbgs18nd/InstallAssistant.pkg"},"MacBookPro17,1":{"installassistant":"https://swcdn.apple.com/content/downloads/45/09/072-97952-A_D4XP9YQOR4/ufl1lu1nuveftnddbv7uvfk6isqbgs18nd/InstallAssistant.pkg"},"MacBookPro18,1":{"installassistant":"https://swcdn.apple.com/content/downloads/45/09/072-97952-A_D4XP9YQOR4/ufl1lu1nuveftnddbv7uvfk6isqbgs18nd/InstallAssistant.pkg"},"MacBookPro18,2":{"installassistant":"https://swcdn.apple.com/content/downloads/45/09/072-97952-A_D4XP9YQOR4/ufl1lu1nuveftnddbv7uvfk6isqbgs18nd/InstallAssistant.pkg"},"MacBookPro18,3":{"installassistant":"https://swcdn.apple.com/content/downloads/45/09/072-97952-A_D4XP9YQOR4/ufl1lu1nuveftnddbv7uvfk6isqbgs18nd/InstallAssistant.pkg"},"MacBookPro18,4":{"installassistant":"https://swcdn.apple.com/content/downloads/45/09/072-97952-A_D4XP9YQOR4/ufl1lu1nuveftnddbv7uvfk6isqbgs18nd/InstallAssistant.pkg"},"Macmini8,1":{"installassistant":"https://swcdn.apple.com/content/downloads/45/09/072-97952-A_D4XP9YQOR4/ufl1lu1nuveftnddbv7uvfk6isqbgs18nd/InstallAssistant.pkg"},"Macmini9,1":{"installassistant":"https://swcdn.apple.com/content/downloads/45/09/072-97952-A_D4XP9YQOR4/ufl1lu1nuveftnddbv7uvfk6isqbgs18nd/InstallAssistant.pkg"},"MacPro7,1":{"installassistant":"https://swcdn.apple.com/content/downloads/45/09/072-97952-A_D4XP9YQOR4/ufl1lu1nuveftnddbv7uvfk6isqbgs18nd/InstallAssistant.pkg"},"MacPro7,1-Rack":{"installassistant":"https://swcdn.apple.com/content/downloads/45/09/072-97952-A_D4XP9YQOR4/ufl1lu1nuveftnddbv7uvfk6isqbgs18nd/InstallAssistant.pkg"},"VirtualMac2,1":{"installassistant":"https://swcdn.apple.com/content/downloads/45/09/072-97952-A_D4XP9YQOR4/ufl1lu1nuveftnddbv7uvfk6isqbgs18nd/InstallAssistant.pkg"}},"appledburl":"https://appledb.dev/firmware/macOS/22H520"}