{"name":"Tesco Clubcard","bundleId":"com.tesco.TescoClubcard","uri":"https://apps.apple.com/gb/app/tesco-clubcard/id351841850","icon":"https://is2-ssl.mzstatic.com/image/thumb/Purple116/v4/63/e6/19/63e61984-cc71-e66a-6e81-b35ad6ca6131/source/512x512bb.jpg","bypasses":[{"guide":"https://hekatos.github.io/tools/tweaks/#liberty-lite-beta","notes":"Not working, causes apps to crash.","repository":{"uri":"https://repos.slim.rocks/repo/?repoUrl=https://ryleyangus.com/repo"},"name":"Liberty Lite (Beta)","appNotes":"Downgrade the app to 3.0.23 with AppStore++, change the version in Info.plist to 3.0.24 and install AppSync Unified. Not working on unc0ver (14.4+)."},{"guide":"https://hekatos.github.io/tools/tweaks/#shadow","repository":{"uri":"https://repos.slim.rocks/repo/?repoUrl=https://ios.jjolano.me"},"name":"Shadow","appNotes":"Enable Lockdown Mode after following the guide."},{"guide":"https://hekatos.github.io/tools/tweaks/#shadow","repository":{"uri":"https://repos.slim.rocks/repo/?repoUrl=https://apt.thebigboss.org/repofiles/cydia"},"name":"HideJB","appNotes":"Disable the \"plus more beta\" option in HideJB."}]}